Constants.py
PytorchKeras.py
pytorchkeras-0.0.2.dist-info/LICENSE.txt
pytorchkeras-0.0.2.dist-info/METADATA
pytorchkeras-0.0.2.dist-info/WHEEL
pytorchkeras-0.0.2.dist-info/top_level.txt
pytorchkeras-0.0.2.dist-info/RECORD
