Metadata-Version: 2.1
Name: pytorchkeras
Version: 0.0.2
Summary: Its a Keras replica for Pytorch
Home-page: https://github.com/malihamza/keras_pytorch
Author: Ali Hamza
Author-email: alihamzakhan94@gmail.com
License: UNKNOWN
Platform: UNKNOWN
Classifier: Programming Language :: Python :: 3
Classifier: Programming Language :: Python :: 3.7
Classifier: Programming Language :: Python :: 3.8
Classifier: Programming Language :: Python :: 3.9
Classifier: Operating System :: OS Independent
Requires-Dist: torch (~=1.7)
